[
  {
    "gender": "male",
    "name": { "title": "Mr", "first": "Krzysztof", "last": "Stingl" },
    "location": {
      "street": { "number": 9513, "name": "Neue Straße" },
      "city": "Leer",
      "state": "Mecklenburg-Vorpommern",
      "country": "Germany",
      "postcode": 33621,
      "coordinates": { "latitude": "-51.9816", "longitude": "-57.7299" },
      "timezone": {
        "offset": "+5:30",
        "description": "Bombay, Calcutta, Madras, New Delhi"
      }
    },
    "email": "krzysztof.stingl@example.com",
    "login": {
      "uuid": "9dbfb774-09ef-4a4e-b801-e6e7866861e1",
      "username": "angrybutterfly934",
      "password": "lillie",
      "salt": "dL37Nq4D",
      "md5": "c868e25db6efd9c9bf03d83092ac2d59",
      "sha1": "0e308e3266d4f0b0efad454bca0f7a5f4a06fb4d",
      "sha256": "e47bda21ef6de50f05efbe170c60030a69d6b9fe9c397aa2a908217d9b06f97e"
    },
    "dob": { "date": "1967-08-01T03:59:21.260Z", "age": 55 },
    "registered": { "date": "2020-03-17T16:57:56.937Z", "age": 2 },
    "phone": "0544-5408181",
    "cell": "0179-7581063",
    "id": { "name": "SVNR", "value": "81 310767 S 137" },
    "picture": {
      "large": "https://randomuser.me/api/portraits/men/48.jpg",
      "medium": "https://randomuser.me/api/portraits/med/men/48.jpg",
      "thumbnail": "https://randomuser.me/api/portraits/thumb/men/48.jpg"
    },
    "nat": "DE"
  },
  {
    "gender": "female",
    "name": { "title": "Miss", "first": "Olga", "last": "Montero" },
    "location": {
      "street": { "number": 2416, "name": "Calle Covadonga" },
      "city": "Córdoba",
      "state": "Comunidad de Madrid",
      "country": "Spain",
      "postcode": 93093,
      "coordinates": { "latitude": "57.0349", "longitude": "-132.3540" },
      "timezone": {
        "offset": "-1:00",
        "description": "Azores, Cape Verde Islands"
      }
    },
    "email": "olga.montero@example.com",
    "login": {
      "uuid": "fc8c10b5-f4c4-4fc9-a633-38e811babca0",
      "username": "crazyladybug712",
      "password": "147852",
      "salt": "HdhSPTWM",
      "md5": "a57adf4a4d2837caa4e97dc025a68e55",
      "sha1": "29f11cca1e153dc3b51cf4811cde2084f02d680b",
      "sha256": "2c398823981195cdc5fff01fdb3faa2d61592e235166169de383558cfa2211d4"
    },
    "dob": { "date": "1973-08-23T00:55:58.267Z", "age": 49 },
    "registered": { "date": "2007-01-12T02:30:09.798Z", "age": 15 },
    "phone": "968-398-167",
    "cell": "635-420-481",
    "id": { "name": "DNI", "value": "16311179-L" },
    "picture": {
      "large": "https://randomuser.me/api/portraits/women/67.jpg",
      "medium": "https://randomuser.me/api/portraits/med/women/67.jpg",
      "thumbnail": "https://randomuser.me/api/portraits/thumb/women/67.jpg"
    },
    "nat": "ES"
  },
  {
    "gender": "female",
    "name": { "title": "Mrs", "first": "Shreedevi", "last": "Bangera" },
    "location": {
      "street": { "number": 3346, "name": "College St" },
      "city": "Ahmednagar",
      "state": "Uttar Pradesh",
      "country": "India",
      "postcode": 96977,
      "coordinates": { "latitude": "-36.9663", "longitude": "-3.0707" },
      "timezone": { "offset": "-9:00", "description": "Alaska" }
    },
    "email": "shreedevi.bangera@example.com",
    "login": {
      "uuid": "a83bae5f-d2ac-4686-816d-23a6223be789",
      "username": "brownwolf705",
      "password": "generic",
      "salt": "TNWsYfmG",
      "md5": "6ff17629ae011d67f190b2a93542f8e4",
      "sha1": "2df9ae536c62c4043e8ea5919d79f56ee22fbbb0",
      "sha256": "00e2cfeae26711efbad0343bc558312406ef632dcd9c7f51bde583a6b23152df"
    },
    "dob": { "date": "1997-09-04T05:13:31.971Z", "age": 25 },
    "registered": { "date": "2005-12-31T04:58:02.215Z", "age": 16 },
    "phone": "7532154895",
    "cell": "8516205807",
    "id": { "name": "UIDAI", "value": "824875801586" },
    "picture": {
      "large": "https://randomuser.me/api/portraits/women/80.jpg",
      "medium": "https://randomuser.me/api/portraits/med/women/80.jpg",
      "thumbnail": "https://randomuser.me/api/portraits/thumb/women/80.jpg"
    },
    "nat": "IN"
  },
  {
    "gender": "female",
    "name": { "title": "Ms", "first": "Kaya", "last": "Rye" },
    "location": {
      "street": { "number": 9557, "name": "Langes gate" },
      "city": "Skien",
      "state": "Aust-Agder",
      "country": "Norway",
      "postcode": "1480",
      "coordinates": { "latitude": "49.4210", "longitude": "-140.5937" },
      "timezone": { "offset": "-12:00", "description": "Eniwetok, Kwajalein" }
    },
    "email": "kaya.rye@example.com",
    "login": {
      "uuid": "91530ffb-ac4d-4138-a3fa-e2d1964287df",
      "username": "heavyduck211",
      "password": "military",
      "salt": "Hgxuckhq",
      "md5": "7a3a977923c9c00ab394cea9761e92cd",
      "sha1": "111e069e31ab10755e24afbd4f0863381fe87cd4",
      "sha256": "2c95a334ced26a067086437a792dd3a0f76e1908ebc42fe29cb21ecebb356e7c"
    },
    "dob": { "date": "1963-05-11T07:19:59.923Z", "age": 59 },
    "registered": { "date": "2014-10-30T01:49:37.527Z", "age": 8 },
    "phone": "59027906",
    "cell": "99290247",
    "id": { "name": "FN", "value": "11056313011" },
    "picture": {
      "large": "https://randomuser.me/api/portraits/women/31.jpg",
      "medium": "https://randomuser.me/api/portraits/med/women/31.jpg",
      "thumbnail": "https://randomuser.me/api/portraits/thumb/women/31.jpg"
    },
    "nat": "NO"
  },
  {
    "gender": "male",
    "name": { "title": "Mr", "first": "Viktor", "last": "Ziblikevich" },
    "location": {
      "street": { "number": 2235, "name": "Samarska" },
      "city": "Krasiliv",
      "state": "Dnipropetrovska",
      "country": "Ukraine",
      "postcode": 53154,
      "coordinates": { "latitude": "7.5828", "longitude": "33.8273" },
      "timezone": {
        "offset": "-3:00",
        "description": "Brazil, Buenos Aires, Georgetown"
      }
    },
    "email": "viktor.ziblikevich@example.com",
    "login": {
      "uuid": "93a409d1-bd37-4cb9-9038-ebb97be0f7b1",
      "username": "heavyleopard246",
      "password": "porter",
      "salt": "8Eejc9nd",
      "md5": "5f5c5fea3b7748f62594b49dfe8be9f3",
      "sha1": "4ce260a55c645800446918a747c5a2b9ca43c828",
      "sha256": "93c1a2a0ff9caddeda3b2ea5abcbe5ed04043bd480fef74169e2e3755dce9232"
    },
    "dob": { "date": "1976-12-08T08:35:12.818Z", "age": 45 },
    "registered": { "date": "2007-11-11T14:40:23.509Z", "age": 15 },
    "phone": "(066) N51-6703",
    "cell": "(068) G30-4890",
    "id": { "name": "", "value": null },
    "picture": {
      "large": "https://randomuser.me/api/portraits/men/64.jpg",
      "medium": "https://randomuser.me/api/portraits/med/men/64.jpg",
      "thumbnail": "https://randomuser.me/api/portraits/thumb/men/64.jpg"
    },
    "nat": "UA"
  },
  {
    "gender": "female",
    "name": { "title": "Ms", "first": "Addison", "last": "Roy" },
    "location": {
      "street": { "number": 3481, "name": "Queen St" },
      "city": "Burlington",
      "state": "Nunavut",
      "country": "Canada",
      "postcode": "N1E 7E5",
      "coordinates": { "latitude": "-54.7464", "longitude": "13.9010" },
      "timezone": {
        "offset": "+9:00",
        "description": "Tokyo, Seoul, Osaka, Sapporo, Yakutsk"
      }
    },
    "email": "addison.roy@example.com",
    "login": {
      "uuid": "15502149-7315-4a57-b03c-e0abe3f147cd",
      "username": "orangegoose561",
      "password": "chrono",
      "salt": "fGPon6pP",
      "md5": "7d8157aee283754bd5fd957554c20305",
      "sha1": "b9f3e8777a32cabb209cf4cc0e677cc25d97037c",
      "sha256": "3aaf8b3fc7b8d36d00cf35bf8e9c40eb5b9cb587ad2dee1a378e08897785c36b"
    },
    "dob": { "date": "1947-08-17T16:44:51.068Z", "age": 75 },
    "registered": { "date": "2021-11-25T03:32:58.776Z", "age": 1 },
    "phone": "Z25 M66-2277",
    "cell": "G22 R57-2050",
    "id": { "name": "SIN", "value": "298439712" },
    "picture": {
      "large": "https://randomuser.me/api/portraits/women/41.jpg",
      "medium": "https://randomuser.me/api/portraits/med/women/41.jpg",
      "thumbnail": "https://randomuser.me/api/portraits/thumb/women/41.jpg"
    },
    "nat": "CA"
  },
  {
    "gender": "male",
    "name": { "title": "Mr", "first": "Aníbal", "last": "Barbosa" },
    "location": {
      "street": { "number": 7626, "name": "Rua Quatro" },
      "city": "Gravataí",
      "state": "Rio Grande do Norte",
      "country": "Brazil",
      "postcode": 32096,
      "coordinates": { "latitude": "42.6093", "longitude": "-121.1877" },
      "timezone": {
        "offset": "+7:00",
        "description": "Bangkok, Hanoi, Jakarta"
      }
    },
    "email": "anibal.barbosa@example.com",
    "login": {
      "uuid": "f32553c7-27f7-4120-b30b-78294a08839c",
      "username": "goldenleopard657",
      "password": "qqqqqqqq",
      "salt": "8eY13Tgb",
      "md5": "df4a3836bfc85f1565b3c8511ffa0ea2",
      "sha1": "f418df276ca386f6b2ed639d6fc6cf93f9b9ff6e",
      "sha256": "d64f7de09a3fe3c7491f5ef1e9d29644eb76d33fe5f43b88846ecc9145ba6038"
    },
    "dob": { "date": "1950-06-01T01:37:18.128Z", "age": 72 },
    "registered": { "date": "2010-11-08T02:19:22.678Z", "age": 12 },
    "phone": "(54) 8614-7700",
    "cell": "(28) 5111-1653",
    "id": { "name": "CPF", "value": "044.482.987-48" },
    "picture": {
      "large": "https://randomuser.me/api/portraits/men/88.jpg",
      "medium": "https://randomuser.me/api/portraits/med/men/88.jpg",
      "thumbnail": "https://randomuser.me/api/portraits/thumb/men/88.jpg"
    },
    "nat": "BR"
  },
  {
    "gender": "female",
    "name": { "title": "Ms", "first": "Una", "last": "Løvoll" },
    "location": {
      "street": { "number": 2777, "name": "Bikuben" },
      "city": "Byrkjelo",
      "state": "Oppland",
      "country": "Norway",
      "postcode": "4312",
      "coordinates": { "latitude": "-75.2752", "longitude": "-57.8918" },
      "timezone": {
        "offset": "-1:00",
        "description": "Azores, Cape Verde Islands"
      }
    },
    "email": "una.lovoll@example.com",
    "login": {
      "uuid": "53507de0-2b0c-4be5-8188-18a33e3a3858",
      "username": "bluegorilla663",
      "password": "raptor",
      "salt": "bOfXgyH7",
      "md5": "653f5fe3f1d8e0f2651cb480256e7736",
      "sha1": "7118013932ebc534e4e5f64da4479bead8e8e55b",
      "sha256": "266f80c36b4a12c16fdeb508c9152d006484c9fa7078ac7570e048ddd4ab49c1"
    },
    "dob": { "date": "1997-11-28T07:59:14.968Z", "age": 25 },
    "registered": { "date": "2014-11-11T20:03:13.484Z", "age": 8 },
    "phone": "72028301",
    "cell": "48842108",
    "id": { "name": "FN", "value": "28119709042" },
    "picture": {
      "large": "https://randomuser.me/api/portraits/women/65.jpg",
      "medium": "https://randomuser.me/api/portraits/med/women/65.jpg",
      "thumbnail": "https://randomuser.me/api/portraits/thumb/women/65.jpg"
    },
    "nat": "NO"
  },
  {
    "gender": "female",
    "name": { "title": "Ms", "first": "Tea", "last": "Giæver" },
    "location": {
      "street": { "number": 2894, "name": "Storoveien" },
      "city": "Snurråsen",
      "state": "Telemark",
      "country": "Norway",
      "postcode": "6155",
      "coordinates": { "latitude": "-80.5620", "longitude": "171.2168" },
      "timezone": {
        "offset": "+3:00",
        "description": "Baghdad, Riyadh, Moscow, St. Petersburg"
      }
    },
    "email": "tea.giaever@example.com",
    "login": {
      "uuid": "6f387a93-4bc4-444a-9c40-91f86bf1c971",
      "username": "sadwolf653",
      "password": "stoner",
      "salt": "Invyi0JR",
      "md5": "19c8f99f6b03abcd507ca441d8e393a6",
      "sha1": "2034cd6270a2ef893c157c4c2db6049935791c98",
      "sha256": "30ad6bc63cedddd1819b73ecfae9d769c79fee260c2227e3d5daf91b2e386ee4"
    },
    "dob": { "date": "1983-12-23T07:26:40.433Z", "age": 38 },
    "registered": { "date": "2006-11-30T10:16:31.185Z", "age": 15 },
    "phone": "69471704",
    "cell": "46433148",
    "id": { "name": "FN", "value": "23128313419" },
    "picture": {
      "large": "https://randomuser.me/api/portraits/women/16.jpg",
      "medium": "https://randomuser.me/api/portraits/med/women/16.jpg",
      "thumbnail": "https://randomuser.me/api/portraits/thumb/women/16.jpg"
    },
    "nat": "NO"
  },
  {
    "gender": "male",
    "name": { "title": "Mr", "first": "Vincent", "last": "Owens" },
    "location": {
      "street": { "number": 4365, "name": "Central St" },
      "city": "Salt Lake City",
      "state": "North Dakota",
      "country": "United States",
      "postcode": 39375,
      "coordinates": { "latitude": "18.7346", "longitude": "40.9845" },
      "timezone": { "offset": "-10:00", "description": "Hawaii" }
    },
    "email": "vincent.owens@example.com",
    "login": {
      "uuid": "cab0c202-7cea-485d-89ee-4b6b9c4bd64a",
      "username": "bluebutterfly698",
      "password": "frogman",
      "salt": "UUw5aeNn",
      "md5": "0cc399ee5a249d0fce8382b94abb1bac",
      "sha1": "4f8e1516499fb75c3dbb99234fd0afdaaf4c12b0",
      "sha256": "a0f6e05c8796a3a7a033a0106854dcf0ec6d7281fdf526856bbb05f8ffb56ced"
    },
    "dob": { "date": "1954-10-15T13:57:55.335Z", "age": 68 },
    "registered": { "date": "2006-10-09T15:57:47.060Z", "age": 16 },
    "phone": "(403) 816-5240",
    "cell": "(631) 677-9268",
    "id": { "name": "SSN", "value": "386-61-6253" },
    "picture": {
      "large": "https://randomuser.me/api/portraits/men/23.jpg",
      "medium": "https://randomuser.me/api/portraits/med/men/23.jpg",
      "thumbnail": "https://randomuser.me/api/portraits/thumb/men/23.jpg"
    },
    "nat": "US"
  },
  {
    "gender": "male",
    "name": { "title": "Mr", "first": "Dwayne", "last": "Lawrence" },
    "location": {
      "street": { "number": 6279, "name": "Westheimer Rd" },
      "city": "Port St. Lucie",
      "state": "Washington",
      "country": "United States",
      "postcode": 13794,
      "coordinates": { "latitude": "4.0660", "longitude": "88.8820" },
      "timezone": {
        "offset": "-7:00",
        "description": "Mountain Time (US & Canada)"
      }
    },
    "email": "dwayne.lawrence@example.com",
    "login": {
      "uuid": "12369c94-33f9-4355-8242-e84945c2fcad",
      "username": "silvergorilla570",
      "password": "porsche1",
      "salt": "2gx6XZ49",
      "md5": "897dd35155f2ad2e85646be45fe489b1",
      "sha1": "5b8c190c1c0630255ca466af743fec576c979a69",
      "sha256": "7c5d6fa2c96a247887e0a8394b2fef5e4a455a7b3b81db08119a5d458560c821"
    },
    "dob": { "date": "1970-01-03T14:15:59.878Z", "age": 52 },
    "registered": { "date": "2016-12-26T05:38:18.473Z", "age": 5 },
    "phone": "(888) 351-1129",
    "cell": "(565) 266-9715",
    "id": { "name": "SSN", "value": "358-34-9042" },
    "picture": {
      "large": "https://randomuser.me/api/portraits/men/88.jpg",
      "medium": "https://randomuser.me/api/portraits/med/men/88.jpg",
      "thumbnail": "https://randomuser.me/api/portraits/thumb/men/88.jpg"
    },
    "nat": "US"
  },
  {
    "gender": "male",
    "name": { "title": "Mr", "first": "Stephen", "last": "Webb" },
    "location": {
      "street": { "number": 2035, "name": "Richmond Park" },
      "city": "Drogheda",
      "state": "South Dublin",
      "country": "Ireland",
      "postcode": 68687,
      "coordinates": { "latitude": "-29.7233", "longitude": "-18.3468" },
      "timezone": {
        "offset": "+8:00",
        "description": "Beijing, Perth, Singapore, Hong Kong"
      }
    },
    "email": "stephen.webb@example.com",
    "login": {
      "uuid": "b07cbf0a-f02e-4e3b-b8e3-2712037b1db9",
      "username": "yellowbird897",
      "password": "pitbull",
      "salt": "5bGFerhT",
      "md5": "c747bc98e7fcba79367e6ea9c1b4bb14",
      "sha1": "20a330d18ed2d1c6ee927f4ffa0e5dbfcfc2e457",
      "sha256": "2706a5636abfb883be875ca118b9e6d5d2808dabf983040947608b4fa3c3f02b"
    },
    "dob": { "date": "1991-04-23T02:01:57.746Z", "age": 31 },
    "registered": { "date": "2007-11-26T09:39:59.323Z", "age": 15 },
    "phone": "061-744-7775",
    "cell": "081-327-3046",
    "id": { "name": "PPS", "value": "9834752T" },
    "picture": {
      "large": "https://randomuser.me/api/portraits/men/1.jpg",
      "medium": "https://randomuser.me/api/portraits/med/men/1.jpg",
      "thumbnail": "https://randomuser.me/api/portraits/thumb/men/1.jpg"
    },
    "nat": "IE"
  },
  {
    "gender": "male",
    "name": { "title": "Monsieur", "first": "Raffael", "last": "Olivier" },
    "location": {
      "street": { "number": 6942, "name": "Avenue du Fort-Caire" },
      "city": "Tamins",
      "state": "Basel-Landschaft",
      "country": "Switzerland",
      "postcode": 7162,
      "coordinates": { "latitude": "-59.9095", "longitude": "-85.8642" },
      "timezone": {
        "offset": "-7:00",
        "description": "Mountain Time (US & Canada)"
      }
    },
    "email": "raffael.olivier@example.com",
    "login": {
      "uuid": "709f0bff-7a3e-4d2b-986e-4c1893fd75fb",
      "username": "whitesnake457",
      "password": "warren",
      "salt": "yIwihKGp",
      "md5": "6ffbf303b2cde28b76d0be75ea8cf47e",
      "sha1": "7571277850482d7726847881ac6e860ada804bf4",
      "sha256": "9b5345da074758c6b6cb7ba6ad7a350ef104b61fa009f5c01a21ede2fefc4008"
    },
    "dob": { "date": "1952-12-26T16:08:57.791Z", "age": 69 },
    "registered": { "date": "2021-10-03T15:27:18.616Z", "age": 1 },
    "phone": "076 031 25 99",
    "cell": "077 182 32 12",
    "id": { "name": "AVS", "value": "756.2966.3635.31" },
    "picture": {
      "large": "https://randomuser.me/api/portraits/men/39.jpg",
      "medium": "https://randomuser.me/api/portraits/med/men/39.jpg",
      "thumbnail": "https://randomuser.me/api/portraits/thumb/men/39.jpg"
    },
    "nat": "CH"
  },
  {
    "gender": "female",
    "name": { "title": "Miss", "first": "Sofía", "last": "Esquivel" },
    "location": {
      "street": { "number": 4680, "name": "Peatonal El Salvador" },
      "city": "Ciudad Acuña",
      "state": "Zacatecas",
      "country": "Mexico",
      "postcode": 70174,
      "coordinates": { "latitude": "-58.9763", "longitude": "-88.2638" },
      "timezone": {
        "offset": "+5:30",
        "description": "Bombay, Calcutta, Madras, New Delhi"
      }
    },
    "email": "sofia.esquivel@example.com",
    "login": {
      "uuid": "822c2914-11dc-495b-bf1c-deb10b58916e",
      "username": "lazyostrich357",
      "password": "wilder",
      "salt": "RLD6TBca",
      "md5": "ccd7da0180d7e276e2a3838c3f8e915b",
      "sha1": "ca2633f36eab53b4e5399af9c237dd2e63ff1441",
      "sha256": "94529881bc1197a3dc5fbba369109cd135e03c32aa96f2675f6ed4002be793d4"
    },
    "dob": { "date": "1985-07-11T17:38:12.184Z", "age": 37 },
    "registered": { "date": "2015-09-26T10:00:32.702Z", "age": 7 },
    "phone": "(686) 393 5905",
    "cell": "(653) 952 8376",
    "id": { "name": "NSS", "value": "16 71 40 2033 5" },
    "picture": {
      "large": "https://randomuser.me/api/portraits/women/61.jpg",
      "medium": "https://randomuser.me/api/portraits/med/women/61.jpg",
      "thumbnail": "https://randomuser.me/api/portraits/thumb/women/61.jpg"
    },
    "nat": "MX"
  },
  {
    "gender": "male",
    "name": { "title": "Mr", "first": "Miroslav", "last": "StanićStanković" },
    "location": {
      "street": { "number": 4216, "name": "Porodice Petrović" },
      "city": "Ruma",
      "state": "Kosovo",
      "country": "Serbia",
      "postcode": 15483,
      "coordinates": { "latitude": "10.3688", "longitude": "-25.0407" },
      "timezone": {
        "offset": "-7:00",
        "description": "Mountain Time (US & Canada)"
      }
    },
    "email": "miroslav.stanicstankovic@example.com",
    "login": {
      "uuid": "ea37bc11-3c91-4222-a950-767d4feb7dcd",
      "username": "bigpanda885",
      "password": "smart",
      "salt": "2UFHUjxu",
      "md5": "962de68cc8ec6d6727e6668459d801e6",
      "sha1": "3e177a5823671bca0cada99dfdcb5290d44f0a85",
      "sha256": "c17928f74b8bce03f6b6ea7d1a23f842401f9688bec35024672a559868f1707a"
    },
    "dob": { "date": "1945-10-08T19:44:55.605Z", "age": 77 },
    "registered": { "date": "2014-03-14T10:23:54.457Z", "age": 8 },
    "phone": "012-5187-932",
    "cell": "066-0519-465",
    "id": { "name": "SID", "value": "722126951" },
    "picture": {
      "large": "https://randomuser.me/api/portraits/men/27.jpg",
      "medium": "https://randomuser.me/api/portraits/med/men/27.jpg",
      "thumbnail": "https://randomuser.me/api/portraits/thumb/men/27.jpg"
    },
    "nat": "RS"
  },
  {
    "gender": "male",
    "name": { "title": "Mr", "first": "Pimen", "last": "Manziy" },
    "location": {
      "street": { "number": 8790, "name": "Uzviz Zamkoviy" },
      "city": "Kiliya",
      "state": "Dnipropetrovska",
      "country": "Ukraine",
      "postcode": 79613,
      "coordinates": { "latitude": "79.7701", "longitude": "7.2910" },
      "timezone": { "offset": "-9:00", "description": "Alaska" }
    },
    "email": "pimen.manziy@example.com",
    "login": {
      "uuid": "e64118d0-a1c1-468f-b26a-faad404d5023",
      "username": "whiteladybug603",
      "password": "3333",
      "salt": "8k8YZbQz",
      "md5": "4fa7a5b5c56d6712bf8323cc27a8c6b3",
      "sha1": "26db37a5c302a6386059794727d3867c11226ddc",
      "sha256": "bd8613d704a656bb1ecfcfb888ee473a04ec341afe845e8f9ed28c847d0e22fe"
    },
    "dob": { "date": "1989-08-24T16:22:43.061Z", "age": 33 },
    "registered": { "date": "2015-07-13T22:53:25.040Z", "age": 7 },
    "phone": "(096) N28-5359",
    "cell": "(097) V03-2265",
    "id": { "name": "", "value": null },
    "picture": {
      "large": "https://randomuser.me/api/portraits/men/4.jpg",
      "medium": "https://randomuser.me/api/portraits/med/men/4.jpg",
      "thumbnail": "https://randomuser.me/api/portraits/thumb/men/4.jpg"
    },
    "nat": "UA"
  }
]
